Metadata-Version: 2.1
Name: django-fsm-2-admin
Version: 2.0.1
Summary: Integrate django-fsm-2 state transitions into the django admin
Home-page: https://github.com/coral-li/django-fsm-2-admin
Author: Coral.li
Author-email: dev@coral.li
License: MIT
Keywords: django fsm admin
Platform: any
Classifier: Development Status :: 5 - Production/Stable
Classifier: Environment :: Web Environment
Classifier: Intended Audience :: Developers
Classifier: License :: OSI Approved :: MIT License
Classifier: Operating System :: OS Independent
Classifier: Framework :: Django
Classifier: Framework :: Django :: 4.2
Classifier: Framework :: Django :: 5.0
Classifier: Framework :: Django :: 5.1
Classifier: Programming Language :: Python
Classifier: Programming Language :: Python :: 3
Classifier: Programming Language :: Python :: 3.8
Classifier: Programming Language :: Python :: 3.9
Classifier: Programming Language :: Python :: 3.10
Classifier: Programming Language :: Python :: 3.11
Classifier: Programming Language :: Python :: 3.12
Classifier: Topic :: Software Development :: Libraries :: Python Modules
License-File: LICENSE
Requires-Dist: Django >=4.2
Requires-Dist: django-fsm-2 >=3.0.0
